[
    {
        "id": 0,
        "question": "متى تكون أيام البيض؟",
        "answers": [
            "1، 2، 3",
            "10، 11، 12",
            "13، 14، 15",
            "آخر 3 أيام من كل شهر"
        ],
        "correctAnswer": 2
    },
    {
        "id": 1,
        "question": "كم عدد ركعات السنة بعد صلاة الجمعة في المسجد؟",
        "answers": [
            "2",
            "4",
            "1",
            "0"
        ],
        "correctAnswer": 1
    },
    {
        "id": 2,
        "question": "كم مرة في اليوم يجب على المسلمين أداء صلاة؟",
        "answers": [
            "3",
            "4",
            "5",
            "6"
        ],
        "correctAnswer": 2
    },
    {
        "id": 3,
        "question": "ما هو اسم الصلاة التي يؤديها المسلمون قبل شروق الشمس؟",
        "answers": [
            "الظهر",
            "العصر",
            "المغرب",
            "الفجر"
        ],
        "correctAnswer": 3
    },
    {
        "id": 4,
        "question": "في أي شهر يصوم المسلمون من الفجر حتى غروب الشمس؟",
        "answers": [
            "شوال",
            "محرم",
            "رمضان",
            "ذو الحجة"
        ],
        "correctAnswer": 2
    },
    {
        "id": 5,
        "question": "ما هو اسم الوجبة التي يأكلها المسلمون قبل بدء صيامهم عند الفجر؟",
        "answers": [
            "الإفطار",
            "السحور",
            "العيد",
            "التراويح"
        ],
        "correctAnswer": 1
    },
    {
        "id": 6,
        "question": "ما هو اسم الزكاة التي يجب على كل مسلم مؤهل دفعها؟",
        "answers": [
            "صدقة",
            "زكاة",
            "خمس",
            "فدية"
        ],
        "correctAnswer": 1
    },
    {
        "id": 7,
        "question": "أي مدينة يجب على المسلمين زيارتها لأداء فريضة الحج؟",
        "answers": [
            "القدس",
            "المدينة",
            "مكة",
            "القاهرة"
        ],
        "correctAnswer": 2
    },
    {
        "id": 8,
        "question": "ما هو اسم الحجر الأسود الذي يطوف حوله المسلمون أثناء الحج؟",
        "answers": [
            "مقام إبراهيم",
            "الحجر الأسود",
            "زمزم",
            "الصفا"
        ],
        "correctAnswer": 1
    },
    {
        "id": 9,
        "question": "ما هو المصطلح الذي يصف الأخلاق والسلوك الحسن في الإسلام؟",
        "answers": [
            "تقوى",
            "أخلاق",
            "إحسان",
            "توكل"
        ],
        "correctAnswer": 1
    },
    {
        "id": 10,
        "question": "ما هو الركن الثاني من أركان الإسلام؟",
        "answers": [
            "الشهادة",
            "الصلاة",
            "الزكاة",
            "الحج"
        ],
        "correctAnswer": 1
    },
    {
        "id": 11,
        "question": "كم مرة في اليوم يجب على المسلم أداء الصلاة؟",
        "answers": [
            "ثلاث مرات",
            "أربع مرات",
            "خمس مرات",
            "ست مرات"
        ],
        "correctAnswer": 2
    },
    {
        "id": 12,
        "question": "في أي شهر يصوم المسلمون من الفجر حتى غروب الشمس؟",
        "answers": [
            "شوال",
            "رمضان",
            "محرم",
            "رجب"
        ],
        "correctAnswer": 1
    },
    {
        "id": 13,
        "question": "ما هو العمل الذي يتضمن إعطاء جزء من الثروة للصدقة؟",
        "answers": [
            "صدقة",
            "زكاة",
            "كفارة",
            "جزية"
        ],
        "correctAnswer": 1
    },
    {
        "id": 14,
        "question": "كم مرة يجب على المسلم أداء فريضة الحج إذا كان قادرًا؟",
        "answers": [
            "مرة واحدة في العمر",
            "مرة في السنة",
            "مرتين في العمر",
            "مرتين في السنة"
        ],
        "correctAnswer": 0
    },
    {
        "id": 15,
        "question": "ما هو اسم الوجبة التي يتم تناولها قبل الفجر خلال شهر رمضان؟",
        "answers": [
            "الإفطار",
            "السحور",
            "التراويح",
            "تهجد"
        ],
        "correctAnswer": 1
    },
    {
        "id": 16,
        "question": "ما هي الصلاة التي يؤديها المسلمون بعد غروب الشمس؟",
        "answers": [
            "الفجر",
            "الظهر",
            "المغرب",
            "العشاء"
        ],
        "correctAnswer": 2
    },
    {
        "id": 17,
        "question": "أي يوم من الأسبوع يعتبر أقدس في الإسلام حيث تقام الصلاة الجماعية؟",
        "answers": [
            "الخميس",
            "الجمعة",
            "السبت",
            "الأحد"
        ],
        "correctAnswer": 1
    },
    {
        "id": 18,
        "question": "ما هي الصلاة الخاصة التي تُؤدى خلال ليالي رمضان؟",
        "answers": [
            "تهجد",
            "تراويح",
            "وتر",
            "ضحى"
        ],
        "correctAnswer": 1
    },
    {
        "id": 19,
        "question": "ما هو المصطلح المستخدم لوصف الزكاة الإلزامية التي يجب على المسلمين دفعها، عادة 2.5% من مدخراتهم؟",
        "answers": [
            "صدقة",
            "كفارة",
            "زكاة",
            "فدية"
        ],
        "correctAnswer": 2
    },
    {
        "id": 20,
        "question": "ما هو اسم الحج الذي يجب على المسلمين أداءه مرة واحدة على الأقل في حياتهم؟",
        "answers": [
            "عمرة",
            "حج",
            "زيارة",
            "رحلة"
        ],
        "correctAnswer": 1
    },
    {
        "id": 21,
        "question": "ما هو اسم الصيام الذي يتم في اليوم العاشر من محرم؟",
        "answers": [
            "صوم",
            "عرفات",
            "عاشوراء",
            "عيد"
        ],
        "correctAnswer": 2
    },
    {
        "id": 22,
        "question": "ما هو المصطلح العربي لمسبحة الصلاة المستخدمة من قبل المسلمين؟",
        "answers": [
            "مسبحة",
            "مسابح",
            "تسبيح",
            "سبحة"
        ],
        "correctAnswer": 2
    },
    {
        "id": 23,
        "question": "أي ركن من أركان الإسلام مرتبط بالشهادة؟",
        "answers": [
            "صلاة",
            "زكاة",
            "حج",
            "شهادة"
        ],
        "correctAnswer": 3
    },
    {
        "id": 24,
        "question": "ما هي أهمية الكعبة في الإسلام؟",
        "answers": [
            "إنها مكان دفن النبي محمد",
            "إنها مسجد بني من قبل أول خليفة",
            "إنها اتجاه المسلمين في الصلاة",
            "إنها مكان مولد الإسلام"
        ],
        "correctAnswer": 2
    },
    {
        "id": 25,
        "question": "أي صلاة تؤدى في الظهيرة؟",
        "answers": [
            "الفجر",
            "الظهر",
            "العصر",
            "العشاء"
        ],
        "correctAnswer": 1
    },
    {
        "id": 26,
        "question": "ما هو المصطلح المستخدم لوصف الطهارة قبل الصلاة؟",
        "answers": [
            "غسل",
            "تيمم",
            "وضوء",
            "استنجاء"
        ],
        "correctAnswer": 2
    },
    {
        "id": 27,
        "question": "ما هو الثواب لأداء عمرة في رمضان؟",
        "answers": [
            "معادل للحج",
            "ضعف ثواب الحج",
            "نصف ثواب الحج",
            "لا يوجد ثواب خاص"
        ],
        "correctAnswer": 0
    },
    {
        "id": 28,
        "question": "ما هو اسم الوجبة المسائية التي يفطر بها المسلمون خلال رمضان؟",
        "answers": [
            "الإفطار",
            "السحور",
            "التراويح",
            "تهجد"
        ],
        "correctAnswer": 0
    },
    {
        "id": 29,
        "question": "ما هو المصطلح للانقطاع الروحي في المسجد خلال الأيام العشرة الأخيرة من رمضان؟",
        "answers": [
            "الإفطار",
            "قيام",
            "اعتكاف",
            "تهجد"
        ],
        "correctAnswer": 2
    },
    {
        "id": 30,
        "question": "ما هو اسم السورة التي تُقرأ في كل وحدة من الصلاة؟",
        "answers": [
            "سورة البقرة",
            "سورة الفاتحة",
            "سورة الإخلاص",
            "سورة يس"
        ],
        "correctAnswer": 1
    },
    {
        "id": 31,
        "question": "ما هو المصطلح للصلاة الجماعية التي تؤدى يوم الجمعة؟",
        "answers": [
            "صلاة العيد",
            "الجمعة",
            "تراويح",
            "قيام"
        ],
        "correctAnswer": 1
    },
    {
        "id": 32,
        "question": "ما هو المصطلح العربي للصلاة الليلية التي تُؤدى بعد العشاء؟",
        "answers": [
            "تهجد",
            "ضحى",
            "قيام",
            "تراويح"
        ],
        "correctAnswer": 0
    },
    {
        "id": 33,
        "question": "أي ركن من أركان الإسلام يتضمن الصيام خلال شهر رمضان؟",
        "answers": [
            "الشهادة",
            "الصلاة",
            "الزكاة",
            "الصوم"
        ],
        "correctAnswer": 3
    },
    {
        "id": 34,
        "question": "ما هي الصلاة الخاصة التي تُؤدى ليلاً خلال الأيام العشرة الأخيرة من رمضان؟",
        "answers": [
            "تهجد",
            "تراويح",
            "وتر",
            "اعتكاف"
        ],
        "correctAnswer": 1
    },
    {
        "id": 35,
        "question": "ما هو اسم الحج الذي يمكن للمسلمين أداءه في أي وقت من السنة؟",
        "answers": [
            "حج",
            "عمرة",
            "زيارة",
            "رحلة"
        ],
        "correctAnswer": 1
    },
    {
        "id": 36,
        "question": "كم عدد الركعات في صلاة الفجر؟",
        "answers": [
            "اثنان",
            "أربعة",
            "ثلاثة",
            "خمسة"
        ],
        "correctAnswer": 0
    },
    {
        "id": 37,
        "question": "ما هو اسم الصلاة التي تُؤدى في وقت منتصف الصباح؟",
        "answers": [
            "ضحى",
            "تهجد",
            "قيام",
            "تراويح"
        ],
        "correctAnswer": 0
    },
    {
        "id": 38,
        "question": "ما هو المصطلح للصدقة التي تُعطى في نهاية رمضان؟",
        "answers": [
            "زكاة",
            "صدقة",
            "فطر",
            "كفارة"
        ],
        "correctAnswer": 2
    },
    {
        "id": 39,
        "question": "ما هو المصطلح للصدقة الواجبة التي تُعطى قبل عيد الفطر؟",
        "answers": [
            "زكاة الفطر",
            "زكاة المال",
            "صدقة",
            "كفارة"
        ],
        "correctAnswer": 0
    },
    {
        "id": 40,
        "question": "ما هو المصطلح للصدقة التطوعية التي يقدمها المسلمون؟",
        "answers": [
            "زكاة",
            "كفارة",
            "صدقة",
            "فدية"
        ],
        "correctAnswer": 2
    },
    {
        "id": 41,
        "question": "ما هو اسم الصلاة التي تُؤدى بعد صلاة الليل الواجبة (العشاء)؟",
        "answers": [
            "ضحى",
            "تهجد",
            "وتر",
            "تراويح"
        ],
        "correctAnswer": 2
    },
    {
        "id": 42,
        "question": "ما هو اسم الحج السنوي إلى مكة الذي يجب على كل مسلم أداءه إذا كان قادرًا؟",
        "answers": [
            "عمرة",
            "حج",
            "زيارة",
            "رحلة"
        ],
        "correctAnswer": 1
    },
    {
        "id": 43,
        "question": "ما هو المصطلح للصلاة الإضافية التي تُؤدى بعد الصلوات الواجبة؟",
        "answers": [
            "سنة",
            "نفل",
            "وتر",
            "تهجد"
        ],
        "correctAnswer": 1
    },
    {
        "id": 44,
        "question": "أي صلاة تُؤدى في وقت الظهيرة المبكرة؟",
        "answers": [
            "فجر",
            "ظهر",
            "عصر",
            "عشاء"
        ],
        "correctAnswer": 1
    },
    {
        "id": 45,
        "question": "ما هو المصطلح العربي للصدقة التي تُعطى لتخليص الشخص من ذنوبه؟",
        "answers": [
            "كفارة",
            "صدقة",
            "فدية",
            "زكاة"
        ],
        "correctAnswer": 0
    },
    {
        "id": 46,
        "question": "ما هو اسم الهيكل الحجري الذي يدور حوله المسلمون خلال الحج؟",
        "answers": [
            "بئر زمزم",
            "الكعبة",
            "منى",
            "عرفات"
        ],
        "correctAnswer": 1
    },
    {
        "id": 47,
        "question": "ما هو المصطلح العربي للصلاة التي تُؤدى عند الغروب؟",
        "answers": [
            "فجر",
            "ظهر",
            "مغرب",
            "عشاء"
        ],
        "correctAnswer": 2
    },
    {
        "id": 48,
        "question": "أي شهر في التقويم الإسلامي هو رمضان؟",
        "answers": [
            "الأول",
            "التاسع",
            "العاشر",
            "الثاني عشر"
        ],
        "correctAnswer": 1
    },
    {
        "id": 49,
        "question": "ما هو المصطلح العربي لخطبة الجمعة؟",
        "answers": [
            "خطبة",
            "سنة",
            "حديث",
            "فتوى"
        ],
        "correctAnswer": 0
    },
    {
        "id": 50,
        "question": "ما هو المصطلح العربي للصلاة المسائية؟",
        "answers": [
            "فجر",
            "ظهر",
            "مغرب",
            "عشاء"
        ],
        "correctAnswer": 3
    },
    {
        "id": 51,
        "question": "ما هو المصطلح للصلاة التي تُؤدى عند الفجر؟",
        "answers": [
            "فجر",
            "ظهر",
            "مغرب",
            "عشاء"
        ],
        "correctAnswer": 0
    },
    {
        "id": 52,
        "question": "ما هو اسم الوجبة التي تُؤكل لكسر الصيام خلال رمضان؟",
        "answers": [
            "إفطار",
            "سحور",
            "تهجد",
            "تراويح"
        ],
        "correctAnswer": 0
    },
    {
        "id": 53,
        "question": "ما هو المصطلح لفعل طلب المغفرة من الله؟",
        "answers": [
            "استغفار",
            "توبة",
            "كفارة",
            "صدقة"
        ],
        "correctAnswer": 1
    },
    {
        "id": 54,
        "question": "ما هو المصطلح للوجبة التي تُؤكل قبل الفجر خلال رمضان؟",
        "answers": [
            "إفطار",
            "سحور",
            "تراويح",
            "تهجد"
        ],
        "correctAnswer": 1
    },
    {
        "id": 55,
        "question": "ما هو المصطلح لفعل غسل النفس قبل الصلاة؟",
        "answers": [
            "غسل",
            "وضوء",
            "تيمم",
            "استنجاء"
        ],
        "correctAnswer": 1
    },
    {
        "id": 56,
        "question": "ما هو المصطلح للصلاة الخاصة التي تُؤدى خلال ليالي رمضان؟",
        "answers": [
            "تهجد",
            "تراويح",
            "وتر",
            "ضحى"
        ],
        "correctAnswer": 1
    },
    {
        "id": 57,
        "question": "ما هو اسم الليلة التي نزل فيها القرآن لأول مرة؟",
        "answers": [
            "ليلة القدر",
            "ليلة الإسراء",
            "ليلة المعراج",
            "ليلة البراءة"
        ],
        "correctAnswer": 0
    },
    {
        "id": 58,
        "question": "ما هو اسم الصلاة التي تُؤدى بعد الصلوات الواجبة؟",
        "answers": [
            "سنة",
            "نفل",
            "وتر",
            "تهجد"
        ],
        "correctAnswer": 1
    },
    {
        "id": 59,
        "question": "ما هو المصطلح العربي للصلاة اليومية الخمس؟",
        "answers": [
            "صوم",
            "زكاة",
            "صلاة",
            "حج"
        ],
        "correctAnswer": 2
    },
    {
        "id": 60,
        "question": "تغيير؟",
        "answers": [
            "فجر",
            "ظهر",
            "عصر",
            "مغرب"
        ],
        "correctAnswer": 1
    },
    {
        "id": 61,
        "question": "ما هو المصطلح العربي للصدقة الواجبة التي يقدمها المسلمون؟",
        "answers": [
            "صدقة",
            "زكاة",
            "صوم",
            "حج"
        ],
        "correctAnswer": 1
    },
    {
        "id": 62,
        "question": "أي من التالي هو عمل عبادي محدد يُؤدى خلال التشهد في الصلاة؟",
        "answers": [
            "تلاوة القرآن بصوت عالٍ",
            "الوقوف للصلاة الإضافية",
            "الجلوس وقراءة الأدعية المحددة",
            "أداء السجود"
        ],
        "correctAnswer": 2
    },    
    {
        "id": 63,
        "question": "ما هو المصطلح العربي للأذان؟",
        "answers": [
            "إمام",
            "أذان",
            "خطبة",
            "إقامة"
        ],
        "correctAnswer": 1
    },
    {
        "id": 64,
        "question": "في سياق الحج، ما اسم الطقوس التي يؤديها الحجاج والتي تشمل الطواف حول الكعبة سبع مرات؟",
        "answers": [
            "الصفا والمروة",
            "الطواف",
            "عرفة",
            "رمي الجمار"
        ],
        "correctAnswer": 1
    },    
    {
        "id": 65,
        "question": "كم عدد الركعات في صلاة الفجر؟",
        "answers": [
            "2",
            "3",
            "4",
            "5"
        ],
        "correctAnswer": 0
    },
    {
        "id": 66,
        "question": "من أي سورة تأتي آية الكرسي؟",
        "answers": [
            "سورة الأحزاب",
            "سورة البقرة",
            "سورة يس",
            "سورة طه"
        ],
        "correctAnswer": 1
    },
    {
        "id": 67,
        "question": "في الفقه الإسلامي، ما هو المصطلح المستخدم للإجماع العلمي على المسائل القانونية؟",
        "answers": [
            "اجتهاد",
            "إجماع",
            "قياس",
            "فتوى"
        ],
        "correctAnswer": 1
    },
    {
        "id": 68,
        "question": "ما هو الحد الأدنى من المال الذي يجعل الزكاة واجبة؟",
        "answers": [
            "نصاب",
            "صدقة",
            "فدية",
            "ربا"
        ],
        "correctAnswer": 0
    },
    {
        "id": 69,
        "question": "أي صلاة تُؤدى في أواخر بعد الظهر؟",
        "answers": [
            "فجر",
            "ظهر",
            "عصر",
            "عشاء"
        ],
        "correctAnswer": 2
    },
    {
        "id": 70,
        "question": "أي سورة يُستحب قراءتها كل يوم جمعة (سنةً)؟",
        "answers": [
            "سورة الإسراء",
            "سورة الكهف",
            "سورة النور",
            "سورة السجدة"
        ],
        "correctAnswer": 1
    },
    {
        "id": 71,
        "question": "أي سورة يُستحب قراءتها كل يوم جمعة (سنةً)؟",
        "answers": [
            "سورة الإسراء",
            "سورة الكهف",
            "سورة النور",
            "سورة السجدة"
        ],
        "correctAnswer": 1
    },
    {
        "id": 72,
        "question": "ما هو اسم الصلاة الليلية الخاصة التي تُؤدى خلال رمضان؟",
        "answers": [
            "تهجد",
            "تراويح",
            "قيام",
            "ضحى"
        ],
        "correctAnswer": 1
    },
    {
        "id": 73,
        "question": "أي صلاة تُؤدى قبل الذهاب إلى النوم مباشرة؟",
        "answers": [
            "مغرب",
            "عشاء",
            "عصر",
            "ظهر"
        ],
        "correctAnswer": 1
    },
    {
        "id": 74,
        "question": "ما هو المصطلح العربي لتطهير المال؟",
        "answers": [
            "صدقة",
            "زكاة",
            "ربا",
            "نصاب"
        ],
        "correctAnswer": 1
    },
    {
        "id": 75,
        "question": "ما هو المصطلح للصوم التطوعي خارج رمضان؟",
        "answers": [
            "نفل",
            "فرض",
            "سنة",
            "واجب"
        ],
        "correctAnswer": 0
    },
    {
        "id": 76,
        "question": "أي شعيرة تتضمن السعي بين جبلي الصفا والمروة خلال الحج؟",
        "answers": [
            "طواف",
            "سعي",
            "رمي",
            "إحرام"
        ],
        "correctAnswer": 1
    },
    {
        "id": 77,
        "question": "ما هو المصطلح المستخدم للتفكير القانوني لاستنباط القوانين الإسلامية من القرآن الكريم والحديث النبوي عندما لا يوجد نص صريح متاح؟",
        "answers": [
            "إجماع",
            "قياس",
            "اجتهاد",
            "فتوى"
        ],
        "correctAnswer": 2
    },
    {
        "id": 78,
        "question": "ما هو المصطلح للصدقة الخاصة التي تُعطى خلال رمضان لمساعدة المحتاجين؟",
        "answers": [
            "صدقات الفطر",
            "زكاة",
            "فدية",
            "كفارة"
        ],
        "correctAnswer": 0
    },
    {
        "id": 79,
        "question": "كم عدد الركعات في صلاة العشاء؟",
        "answers": [
            "2",
            "3",
            "4",
            "5"
        ],
        "correctAnswer": 2
    },
    {
        "id": 80,
        "question": "ما اسم الصلاة التي تؤدى عند الظهر؟",
        "answers": [
            "الفجر",
            "الظهر",
            "العصر",
            "المغرب"
        ],
        "correctAnswer": 1
    },
    {
        "id": 81,
        "question": "ما هو المصطلح العربي لصيام الأيام المستحبّة يومي الاثنين والخميس؟",
        "answers": [
            "صوم التطوع",
            "صوم الكفارة",
            "صوم القضاء",
            "صوم النفل"
        ],
        "correctAnswer": 3
    },
    {
        "id": 82,
        "question": "أي صلاة يتم قصرها وجمعها أثناء السفر؟",
        "answers": [
            "الفجر",
            "الظهر والعصر",
            "المغرب والعشاء",
            "كل ما سبق"
        ],
        "correctAnswer": 3
    },
    {
        "id": 83,
        "question": "ما هو المصطلح الذي يشير إلى إعطاء جزء من المحصول للفقراء؟",
        "answers": [
            "زكاة المال",
            "عشر",
            "فدية",
            "نصاب"
        ],
        "correctAnswer": 1
    },
    {
        "id": 84,
        "question": "ما هو الطواف حول الكعبة سبع مرات يسمى؟",
        "answers": [
            "طواف",
            "سعي",
            "رمي",
            "إحرام"
        ],
        "correctAnswer": 0
    },
    {
        "id": 85,
        "question": "ما هو المصطلح للصلاة الزائدة التي تؤدى في الثلث الأخير من الليل؟",
        "answers": [
            "تهجد",
            "تراويح",
            "وتر",
            "عشاء"
        ],
        "correctAnswer": 0
    },
    {
        "id": 86,
        "question": "ما هو الأجر الذي يُعطى لمن يصوم ستة أيام من شوال؟",
        "answers": [
            "حج مبرور",
            "عمرة",
            "ثواب",
            "بركة"
        ],
        "correctAnswer": 2
    },
    {
        "id": 87,
        "question": "ما هو المصطلح لصيام يوم عرفة لغير الحجاج؟",
        "answers": [
            "صوم النفل",
            "صوم الكفارة",
            "صوم الأيام البيض",
            "صوم عرفة"
        ],
        "correctAnswer": 3
    },
    {
        "id": 88,
        "question": "ما هو المصطلح للصيام الواجب بسبب كسر نذر؟",
        "answers": [
            "صوم التطوع",
            "صوم الكفارة",
            "صوم القضاء",
            "صوم النفل"
        ],
        "correctAnswer": 1
    },
    {
        "id": 89,
        "question": "ما اسم الماء الذي يعتبر مقدسًا ويأتي من بئر في مكة؟",
        "answers": [
            "زمزم",
            "الصفا",
            "المروة",
            "نصاب"
        ],
        "correctAnswer": 0
    },
    {
        "id": 90,
        "question": "ما هو المصطلح للصلاة التطوعية التي تؤدى للحاجات أو الطلبات الخاصة؟",
        "answers": [
            "ضحى",
            "توبة",
            "استخارة",
            "صلاة الحاجة"
        ],
        "correctAnswer": 3
    },
    {
        "id": 91,
        "question": "ما هو المصطلح للصلاة التي تؤدى بعد المغرب؟",
        "answers": [
            "الفجر",
            "الظهر",
            "العصر",
            "العشاء"
        ],
        "correctAnswer": 3
    },
    {
        "id": 92,
        "question": "ما هو المصطلح للصلاة الزائدة التي تؤدى في العشر الأواخر من رمضان؟",
        "answers": [
            "تهجد",
            "تراويح",
            "قيام الليل",
            "اعتكاف"
        ],
        "correctAnswer": 2
    },
    {
        "id": 93,
        "question": "ما هو المصطلح للوضوء الذي يتم باستخدام التراب أو الغبار النظيف عند عدم توفر الماء؟",
        "answers": [
            "غسل",
            "وضوء",
            "تيمم",
            "استنجاء"
        ],
        "correctAnswer": 2
    },
    {
        "id": 94,
        "question": "أي من التالي هو نوع من الصدقة التي تعطى في السر للحفاظ على كرامة المستلم؟",
        "answers": [
            "زكاة",
            "صدقة السر",
            "كفارة",
            "فدية"
        ],
        "correctAnswer": 1
    },
    {
        "id": 95,
        "question": "ما هو المصطلح العربي للعمرة التي يمكن أداؤها في أي وقت من السنة؟",
        "answers": [
            "حج",
            "عمرة",
            "زيارة",
            "رحلة"
        ],
        "correctAnswer": 1
    },
    {
        "id": 96,
        "question": "ما هو المصطلح للشعيرة التي تتضمن رمي الجمار أثناء الحج؟",
        "answers": [
            "طواف",
            "سعي",
            "رمي الجمار",
            "إحرام"
        ],
        "correctAnswer": 2
    },
    {
        "id": 97,
        "question": "ما هو المصطلح للصلاة الخاصة التي تؤدى لطلب الإرشاد في اتخاذ قرار؟",
        "answers": [
            "صلاة التوبة",
            "صلاة الاستخارة",
            "صلاة الحاجة",
            "صلاة التسبيح"
        ],
        "correctAnswer": 1
    },
    {
        "id": 98,
        "question": "ما هو المصطلح للصلاة التطوعية التي تؤدى بعد الصلوات الواجبة؟",
        "answers": [
            "سنة",
            "نفل",
            "وتر",
            "تهجد"
        ],
        "correctAnswer": 0
    },
    {
        "id": 99,
        "question": "ما هو المصطلح العربي للزكاة الواجبة التي تعطى في نهاية رمضان؟",
        "answers": [
            "زكاة الفطر",
            "زكاة المال",
            "صدقة",
            "كفارة"
        ],
        "correctAnswer": 0
    }
]