[
    {
        "id": 0,
        "question": "في أي عام وُلد النبي محمد (صلى الله عليه وسلم)؟",
        "answers": [
            "570 م",
            "580 م",
            "590 م",
            "600 م"
        ],
        "correctAnswer": 0
    },
    {
        "id": 1,
        "question": "ما هو اسم الغار الذي تلقى فيه النبي محمد (صلى الله عليه وسلم) أول وحي؟",
        "answers": [
            "غار حراء",
            "غار ثور",
            "غار صبر",
            "غار قُراء"
        ],
        "correctAnswer": 0
    },
    {
        "id": 2,
        "question": "من كانت الزوجة الأولى للنبي محمد (صلى الله عليه وسلم)؟",
        "answers": [
            "عائشة",
            "حفصة",
            "خديجة",
            "زينب"
        ],
        "correctAnswer": 2
    },
    {
        "id": 3,
        "question": "ما هي المدينة المعروفة بمكان هجرة النبي؟",
        "answers": [
            "مكة",
            "الطائف",
            "يثرب (المدينة المنورة)",
            "القدس"
        ],
        "correctAnswer": 2
    },
    {
        "id": 4,
        "question": "ما هو اسم عم النبي محمد (صلى الله عليه وسلم) الذي رعاه بعد جده؟",
        "answers": [
            "أبو لهب",
            "أبو طالب",
            "أبو سفيان",
            "عبد الله"
        ],
        "correctAnswer": 1
    },
    {
        "id": 5,
        "question": "من كان أول شخص يقبل الإسلام؟",
        "answers": [
            "أبو بكر",
            "علي بن أبي طالب",
            "خديجة",
            "عمر بن الخطاب"
        ],
        "correctAnswer": 2
    },
    {
        "id": 6,
        "question": "في أي معركة قاتل المسلمون لأول مرة ضد قريش؟",
        "answers": [
            "معركة أحد",
            "معركة بدر",
            "معركة الخندق",
            "معركة حنين"
        ],
        "correctAnswer": 1
    },
    {
        "id": 7,
        "question": "ما هو الاتفاق الذي تم توقيعه بين المسلمين وقريش في سنة 628 م؟",
        "answers": [
            "صلح الحديبية",
            "صلح بدر",
            "صلح أحد",
            "صلح مكة"
        ],
        "correctAnswer": 0
    },
    {
        "id": 8,
        "question": "ما هو أول مسجد بناه النبي محمد (صلى الله عليه وسلم)؟",
        "answers": [
            "المسجد الحرام",
            "المسجد الأقصى",
            "مسجد قباء",
            "المسجد النبوي"
        ],
        "correctAnswer": 2
    },
    {
        "id": 9,
        "question": "أي معركة تُعرف كنقطة تحول في الفتوحات الإسلامية المبكرة؟",
        "answers": [
            "معركة بدر",
            "معركة أحد",
            "معركة الخندق",
            "معركة خيبر"
        ],
        "correctAnswer": 0
    },
    {
        "id": 10,
        "question": "من كان أول خليفة بعد وفاة النبي محمد (صلى الله عليه وسلم)؟",
        "answers": [
            "عمر بن الخطاب",
            "علي بن أبي طالب",
            "أبو بكر الصديق",
            "عثمان بن عفان"
        ],
        "correctAnswer": 2
    },
    {
        "id": 11,
        "question": "أي خليفة كان معروفًا بجمع القرآن في كتاب واحد؟",
        "answers": [
            "أبو بكر الصديق",
            "عمر بن الخطاب",
            "عثمان بن عفان",
            "علي بن أبي طالب"
        ],
        "correctAnswer": 2
    },
    {
        "id": 12,
        "question": "أي خليفة أسس التقويم الإسلامي؟",
        "answers": [
            "أبو بكر الصديق",
            "عمر بن الخطاب",
            "عثمان بن عفان",
            "علي بن أبي طالب"
        ],
        "correctAnswer": 1
    },
    {
        "id": 13,
        "question": "من كان الخليفة الثاني للإسلام؟",
        "answers": [
            "أبو بكر الصديق",
            "عمر بن الخطاب",
            "عثمان بن عفان",
            "علي بن أبي طالب"
        ],
        "correctAnswer": 1
    },
    {
        "id": 14,
        "question": "أي خليفة كان معروفًا بإصلاحاته القضائية الواسعة؟",
        "answers": [
            "أبو بكر الصديق",
            "عمر بن الخطاب",
            "عثمان بن عفان",
            "علي بن أبي طالب"
        ],
        "correctAnswer": 1
    },
    {
        "id": 15,
        "question": "من كان الخليفة الثالث للإسلام؟",
        "answers": [
            "أبو بكر الصديق",
            "عمر بن الخطاب",
            "عثمان بن عفان",
            "علي بن أبي طالب"
        ],
        "correctAnswer": 2
    },
    {
        "id": 16,
        "question": "من كان الخليفة الرابع للإسلام؟",
        "answers": [
            "أبو بكر الصديق",
            "عمر بن الخطاب",
            "عثمان بن عفان",
            "علي بن أبي طالب"
        ],
        "correctAnswer": 3
    },
    {
        "id": 17,
        "question": "أي خليفة نقل العاصمة الإسلامية إلى الكوفة؟",
        "answers": [
            "أبو بكر الصديق",
            "عمر بن الخطاب",
            "عثمان بن عفان",
            "علي بن أبي طالب"
        ],
        "correctAnswer": 3
    },
    {
        "id": 18,
        "question": "أي معركة تعتبر أول حرب أهلية في تاريخ الإسلام؟",
        "answers": [
            "معركة بدر",
            "معركة أحد",
            "معركة صفين",
            "معركة الجمل"
        ],
        "correctAnswer": 3
    },
    {
        "id": 19,
        "question": "من كان والي سوريا خلال خلافة عمر بن الخطاب؟",
        "answers": [
            "معاوية بن أبي سفيان",
            "يزيد بن معاوية",
            "عمرو بن العاص",
            "خالد بن الوليد"
        ],
        "correctAnswer": 0
    },
    {
        "id": 20,
        "question": "أي إمبراطورية إسلامية كانت معروفة بعاصمتها بغداد؟",
        "answers": [
            "الخلافة الأموية",
            "الخلافة العباسية",
            "الدولة العثمانية",
            "الخلافة الفاطمية"
        ],
        "correctAnswer": 1
    },
    {
        "id": 21,
        "question": "من هو مؤسس الخلافة الأموية؟",
        "answers": [
            "معاوية بن أبي سفيان",
            "عبد الملك بن مروان",
            "عمر بن عبد العزيز",
            "مروان بن الحكم"
        ],
        "correctAnswer": 0
    },
    {
        "id": 22,
        "question": "أي مدينة كانت عاصمة الخلافة الأموية؟",
        "answers": [
            "مكة",
            "المدينة",
            "دمشق",
            "بغداد"
        ],
        "correctAnswer": 2
    },
    {
        "id": 23,
        "question": "من كان أول خليفة في الخلافة العباسية؟",
        "answers": [
            "أبو العباس السفاح",
            "هارون الرشيد",
            "المأمون",
            "المنصور"
        ],
        "correctAnswer": 0
    },
    {
        "id": 24,
        "question": "أي مدينة كانت عاصمة الخلافة العباسية؟",
        "answers": [
            "دمشق",
            "بغداد",
            "القاهرة",
            "إسطنبول"
        ],
        "correctAnswer": 1
    },
    {
        "id": 25,
        "question": "من كان أشهر حاكم في الخلافة العباسية المعروف برعايته للفنون والعلوم؟",
        "answers": [
            "المأمون",
            "هارون الرشيد",
            "المنصور",
            "المتوكل"
        ],
        "correctAnswer": 1
    },
    {
        "id": 26,
        "question": "أي إمبراطورية إسلامية كانت معروفة بعاصمتها القسطنطينية؟",
        "answers": [
            "الخلافة الأموية",
            "الخلافة العباسية",
            "الإمبراطورية العثمانية",
            "الخلافة الفاطمية"
        ],
        "correctAnswer": 2
    },
    {
        "id": 27,
        "question": "من هو مؤسس الإمبراطورية العثمانية؟",
        "answers": [
            "عثمان الأول",
            "محمد الفاتح",
            "سليمان القانوني",
            "سليم الأول"
        ],
        "correctAnswer": 0
    },
    {
        "id": 28,
        "question": "أي سلطان عثماني فتح القسطنطينية؟",
        "answers": [
            "عثمان الأول",
            "محمد الفاتح",
            "سليمان القانوني",
            "سليم الأول"
        ],
        "correctAnswer": 1
    },
    {
        "id": 29,
        "question": "أي إمبراطورية كانت معروفة ببناء المسجد الأزرق؟",
        "answers": [
            "الخلافة الأموية",
            "الخلافة العباسية",
            "الإمبراطورية العثمانية",
            "الخلافة الفاطمية"
        ],
        "correctAnswer": 2
    },
    {
        "id": 30,
        "question": "من كان السلطان العثماني المشهور بإصلاحاته القانونية وإنجازاته الثقافية؟",
        "answers": [
            "عثمان الأول",
            "محمد الفاتح",
            "سليمان القانوني",
            "سليم الأول"
        ],
        "correctAnswer": 2
    },
    {
        "id": 31,
        "question": "أي إمبراطورية كانت مسؤولة عن إنشاء جامعة الأزهر؟",
        "answers": [
            "الخلافة الأموية",
            "الخلافة العباسية",
            "الخلافة الفاطمية",
            "الإمبراطورية العثمانية"
        ],
        "correctAnswer": 2
    },
    {
        "id": 32,
        "question": "أي خلافة إسلامية معروفة بتطوير الأسطرلاب؟",
        "answers": [
            "الخلافة الأموية",
            "الخلافة العباسية",
            "الخلافة الفاطمية",
            "الإمبراطورية العثمانية"
        ],
        "correctAnswer": 1
    },
    {
        "id": 33,
        "question": "أي مكتبة مشهورة أنشئت خلال الخلافة العباسية؟",
        "answers": [
            "بيت الحكمة",
            "مكتبة الإسكندرية",
            "المكتبة الكبرى ببغداد",
            "مكتبة قرطبة"
        ],
        "correctAnswer": 0
    },
    {
        "id": 34,
        "question": "أي خلافة معروفة ببناء المسجد الكبير في قرطبة؟",
        "answers": [
            "الخلافة الأموية",
            "الخلافة العباسية",
            "الخلافة الفاطمية",
            "الإمبراطورية العثمانية"
        ],
        "correctAnswer": 0
    },
    {
        "id": 35,
        "question": "أي إمبراطورية كانت مسؤولة عن بناء الحمراء في إسبانيا؟",
        "answers": [
            "الخلافة الأموية",
            "الخلافة العباسية",
            "الخلافة الفاطمية",
            "مملكة غرناطة النصيرية"
        ],
        "correctAnswer": 3
    },
    {
        "id": 36,
        "question": "أي عالم إسلامي معروف بأنه 'أبو الجبر'؟",
        "answers": [
            "الكندي",
            "الخوارزمي",
            "ابن سينا",
            "الفارابي"
        ],
        "correctAnswer": 1
    },
    {
        "id": 37,
        "question": "أي عالم إسلامي كتب الموسوعة الطبية المشهورة 'القانون في الطب'؟",
        "answers": [
            "الرازي",
            "ابن سينا (أفيسينا)",
            "البيروني",
            "الكندي"
        ],
        "correctAnswer": 1
    },
    {
        "id": 38,
        "question": "من هو الفيلسوف المسلم الشهير المعروف بأعماله على أرسطو؟",
        "answers": [
            "الغزالي",
            "الكندي",
            "ابن رشد (أفيروس)",
            "الفارابي"
        ],
        "correctAnswer": 2
    },
    {
        "id": 39,
        "question": "أي جغرافي إسلامي كتب 'كتاب المسالك والممالك'؟",
        "answers": [
            "ابن بطوطة",
            "الإدريسي",
            "ابن جبير",
            "المسعودي"
        ],
        "correctAnswer": 3
    },
    {
        "id": 40,
        "question": "من هو مؤلف كتاب الرحلات 'الرحلة'؟",
        "answers": [
            "ابن بطوطة",
            "ابن جبير",
            "الإدريسي",
            "المسعودي"
        ],
        "correctAnswer": 0
    },
    {
        "id": 41,
        "question": "أي عالم إسلامي معروف بإسهاماته الهامة في البصريات؟",
        "answers": [
            "الكندي",
            "الحسن بن الهيثم (الهازن)",
            "الرازي",
            "ابن سينا"
        ],
        "correctAnswer": 1
    },
    {
        "id": 42,
        "question": "أي عالم مسلم متعدد المعارف معروف بأعماله في الطب والفلك والكيمياء؟",
        "answers": [
            "البيروني",
            "الرازي",
            "الخوارزمي",
            "ابن سينا"
        ],
        "correctAnswer": 1
    },
    {
        "id": 43,
        "question": "أي إمبراطورية معروفة بتطوير الأسطرلاب؟",
        "answers": [
            "الخلافة الأموية",
            "الخلافة العباسية",
            "الخلافة الفاطمية",
            "مملكة غرناطة النصيرية"
        ],
        "correctAnswer": 1
    },
    {
        "id": 44,
        "question": "أي مكتبة مشهورة أنشئت خلال الخلافة العباسية؟",
        "answers": [
            "بيت الحكمة",
            "مكتبة الإسكندرية",
            "المكتبة الكبرى ببغداد",
            "مكتبة قرطبة"
        ],
        "correctAnswer": 0
    },
    {
        "id": 45,
        "question": "أي خلافة معروفة ببناء المسجد الكبير في قرطبة؟",
        "answers": [
            "الخلافة الأموية",
            "الخلافة العباسية",
            "الخلافة الفاطمية",
            "الإمبراطورية العثمانية"
        ],
        "correctAnswer": 0
    },
    {
        "id": 46,
        "question": "من هو الرحالة المسلم المشهور الذي زار أكثر من 40 دولة؟",
        "answers": [
            "الإدريسي",
            "ابن جبير",
            "المسعودي",
            "ابن بطوطة"
        ],
        "correctAnswer": 3
    },
    {
        "id": 47,
        "question": "أي مدينة إسلامية أصبحت مركزًا رئيسيًا للتعلم خلال العصر الذهبي للإسلام؟",
        "answers": [
            "مكة",
            "المدينة",
            "بغداد",
            "دمشق"
        ],
        "correctAnswer": 2
    },
    {
        "id": 48,
        "question": "أي إمبراطورية كانت مسؤولة عن بناء المسجد الأزرق في إسطنبول؟",
        "answers": [
            "الخلافة الأموية",
            "الخلافة العباسية",
            "الخلافة الفاطمية",
            "الإمبراطورية العثمانية"
        ],
        "correctAnswer": 3
    },
    {
        "id": 49,
        "question": "من هو الفيلسوف المسلم المعروف بأعماله على أفلاطون وأرسطو؟",
        "answers": [
            "الغزالي",
            "الكندي",
            "ابن رشد (أفيروس)",
            "الفارابي"
        ],
        "correctAnswer": 3
    },
    {
        "id": 50,
        "question": "من هو العالم المسلم الشهير المعروف بعمله 'كتاب الشفاء'؟",
        "answers": [
            "الفارابي",
            "الكندي",
            "ابن سينا (أفيسينا)",
            "الرازي"
        ],
        "correctAnswer": 2
    },
    {
        "id": 51,
        "question": "أي خلافة إسلامية معروفة بعاصمتها القاهرة؟",
        "answers": [
            "الخلافة الأموية",
            "الخلافة العباسية",
            "الخلافة الفاطمية",
            "الإمبراطورية العثمانية"
        ],
        "correctAnswer": 2
    },
    {
        "id": 52,
        "question": "أي عالم إسلامي معروف بمساهماته في مجال الجراحة؟",
        "answers": [
            "ابن سينا",
            "الزهراوي (ألبوكاسيس)",
            "الرازي",
            "الغزالي"
        ],
        "correctAnswer": 1
    },
    {
        "id": 53,
        "question": "من هو الصحابي الذي فداه الرسول بأبيه وأمه؟",
        "answers": [
            "علي بن أبي طالب",
            "سعد بن مالك",
            "عبد الله بن جعفر",
            "عبد الله بن عباس"
        ],
        "correctAnswer": 1
    },
    {
        "id": 54,
        "question": "أي معركة خاضها النبي (صلى الله عليه وسلم) لأول مرة؟",
        "answers": [
            "معركة تبوك",
            "معركة أحد",
            "معركة بدر",
            "معركة الأحزاب"
        ],
        "correctAnswer": 2
    },
    {
        "id": 55,
        "question": "أي مدينة أسستها الخلافة الأموية كعاصمتها؟",
        "answers": [
            "بغداد",
            "مكة",
            "دمشق",
            "القاهرة"
        ],
        "correctAnswer": 2
    },
    {
        "id": 56,
        "question": "أي إمبراطورية إسلامية معروفة بمساهماتها الكبيرة في الرياضيات والعلوم خلال العصر الذهبي للإسلام؟",
        "answers": [
            "الإمبراطورية العثمانية",
            "الإمبراطورية المغولية",
            "الخلافة العباسية",
            "الخلافة الفاطمية"
        ],
        "correctAnswer": 2
    },
    {
        "id": 57,
        "question": "أي خليفة من الخلفاء الراشدين كان معروفًا بجمع القرآن في كتاب واحد؟",
        "answers": [
            "أبو بكر",
            "عمر بن الخطاب",
            "عثمان بن عفان",
            "علي بن أبي طالب"
        ],
        "correctAnswer": 2
    },
    {
        "id": 58,
        "question": "من هو العالم المسلم الشهير المعروف بأبو الجبر؟",
        "answers": [
            "الكندي",
            "ابن سينا",
            "الخوارزمي",
            "الفارابي"
        ],
        "correctAnswer": 2
    },
    {
        "id": 59,
        "question": "ما هي اللغة الرئيسية للإدارة والعلم خلال الخلافة العباسية؟",
        "answers": [
            "الفارسية",
            "التركية",
            "العربية",
            "اللاتينية"
        ],
        "correctAnswer": 2
    },
    {
        "id": 60,
        "question": "أي إمبراطورية إسلامية حكمت شبه القارة الهندية وتعرف بمعالمها المعمارية مثل تاج محل؟",
        "answers": [
            "الخلافة الأموية",
            "الخلافة العباسية",
            "الإمبراطورية العثمانية",
            "الإمبراطورية المغولية"
        ],
        "correctAnswer": 3
    },
    {
        "id": 61,
        "question": "من هو أطول حكام العثمانيين حكمًا؟",
        "answers": [
            "سليمان القانوني",
            "محمد الفاتح",
            "سليم الأول",
            "بايزيد الثاني"
        ],
        "correctAnswer": 0
    },
    {
        "id": 62,
        "question": "ما هو اسم المعركة التي جرح فيها النبي (صلى الله عليه وسلم) ولكن المسلمين أظهروا فيها الصمود؟",
        "answers": [
            "معركة بدر",
            "معركة أحد",
            "معركة الخندق",
            "معركة تبوك"
        ],
        "correctAnswer": 1
    },
    {
        "id": 63,
        "question": "من كانت مرضعة النبي محمد (صلى الله عليه وسلم)؟",
        "answers": [
            "حليمة السعدية",
            "بركة",
            "آمنة",
            "فاطمة"
        ],
        "correctAnswer": 0
    },
    {
        "id": 64,
        "question": "أي خليفة معروف بفتح القدس؟",
        "answers": [
            "أبو بكر الصديق",
            "عمر بن الخطاب",
            "عثمان بن عفان",
            "علي بن أبي طالب"
        ],
        "correctAnswer": 1
    },
    {
        "id": 65,
        "question": "أي معركة تعرف أيضًا بمعركة الخندق؟",
        "answers": [
            "معركة بدر",
            "معركة أحد",
            "معركة الخندق",
            "معركة تبوك"
        ],
        "correctAnswer": 2
    },
    {
        "id": 66,
        "question": "من هو الخليفة الرابع في الخلافة الأموية؟",
        "answers": [
            "معاوية الأول",
            "يزيد الأول",
            "عبد الملك",
            "مروان الأول"
        ],
        "correctAnswer": 2
    },
    {
        "id": 67,
        "question": "أي خليفة عباسي معروف بحركة الترجمة ورعاية العلماء؟",
        "answers": [
            "المنصور",
            "هارون الرشيد",
            "المأمون",
            "المتوكل"
        ],
        "correctAnswer": 2
    },
    {
        "id": 68,
        "question": "أي عالم إسلامي معروف بعمله 'كتاب الجبر والمقابلة'؟",
        "answers": [
            "الكندي",
            "الخوارزمي",
            "ابن سينا",
            "الفارابي"
        ],
        "correctAnswer": 1
    },
    {
        "id": 69,
        "question": "أي خلافة معروفة ببناء قبة الصخرة؟",
        "answers": [
            "الخلافة الأموية",
            "الخلافة العباسية",
            "الخلافة الفاطمية",
            "الإمبراطورية العثمانية"
        ],
        "correctAnswer": 0
    },
    {
        "id": 70,
        "question": "من هو أول خليفة يتم اغتياله؟",
        "answers": [
            "أبو بكر الصديق",
            "عمر بن الخطاب",
            "عثمان بن عفان",
            "علي بن أبي طالب"
        ],
        "correctAnswer": 2
    },
    {
        "id": 71,
        "question": "أي عالم إسلامي قدم مساهمات كبيرة في فهم البصر والبصريات؟",
        "answers": [
            "الكندي",
            "ابن سينا",
            "الحسن بن الهيثم",
            "الرازي"
        ],
        "correctAnswer": 2
    },
    {
        "id": 72,
        "question": "أي إمبراطورية إسلامية معروفة بقانون 'قانون' والإصلاحات تحت حكم سليمان القانوني؟",
        "answers": [
            "الخلافة الأموية",
            "الخلافة العباسية",
            "الإمبراطورية العثمانية",
            "الخلافة الفاطمية"
        ],
        "correctAnswer": 2
    },
    {
        "id": 73,
        "question": "من هو الرحالة المسلم الشهير الذي سافر بشكل واسع عبر أفريقيا وأوروبا وآسيا؟",
        "answers": [
            "ابن جبير",
            "المسعودي",
            "ابن بطوطة",
            "الإدريسي"
        ],
        "correctAnswer": 2
    },
    {
        "id": 74,
        "question": "أي معركة خاضها المسلمون ضد قريش بعد انتصارهم في بدر؟",
        "answers": [
            "معركة أحد",
            "معركة الخندق",
            "معركة حنين",
            "معركة تبوك"
        ],
        "correctAnswer": 0
    },
    {
        "id": 75,
        "question": "من هو أول خليفة من بني هاشم؟",
        "answers": [
            "أبو بكر الصديق",
            "عمر بن الخطاب",
            "عثمان بن عفان",
            "علي بن أبي طالب"
        ],
        "correctAnswer": 3
    },
    {
        "id": 76,
        "question": "أي خلافة معروفة بإنشاء 'بيت الحكمة' في بغداد؟",
        "answers": [
            "الخلافة الأموية",
            "الخلافة العباسية",
            "الخلافة الفاطمية",
            "الإمبراطورية العثمانية"
        ],
        "correctAnswer": 1
    },
    {
        "id": 77,
        "question": "من هو الخليفة الأموي الذي قام ببناء المسجد الأموي في دمشق؟",
        "answers": [
            "عبد الملك بن مروان",
            "الوليد بن عبد الملك",
            "سليمان بن عبد الملك",
            "عمر بن عبد العزيز"
        ],
        "correctAnswer": 1
    },
    {
        "id": 78,
        "question": "أي مدينة عرفت باسم 'مدينة السلام'؟",
        "answers": [
            "مكة",
            "دمشق",
            "بغداد",
            "القاهرة"
        ],
        "correctAnswer": 2
    },
    {
        "id": 79,
        "question": "أي عالم إسلامي معروف بمساهماته في علم الكيمياء؟",
        "answers": [
            "الخوارزمي",
            "الزهراوي",
            "جابر بن حيان",
            "الفارابي"
        ],
        "correctAnswer": 2
    },
    {
        "id": 80,
        "question": "أي خليفة راشدي قتل أثناء الصلاة؟",
        "answers": [
            "أبو بكر الصديق",
            "عمر بن الخطاب",
            "عثمان بن عفان",
            "علي بن أبي طالب"
        ],
        "correctAnswer": 1
    },
    {
        "id": 81,
        "question": "أي إمبراطورية إسلامية معروفة بغزواتها العسكرية في أوروبا، بما في ذلك معركة ملاذكرد؟",
        "answers": [
            "الخلافة الأموية",
            "الخلافة العباسية",
            "الخلافة الفاطمية",
            "الإمبراطورية السلجوقية"
        ],
        "correctAnswer": 3
    },
    {
        "id": 82,
        "question": "أي معركة أنهت هيمنة الإمبراطورية البيزنطية في الأناضول؟",
        "answers": [
            "معركة اليرموك",
            "معركة ملاذكرد",
            "معركة تور",
            "معركة حطين"
        ],
        "correctAnswer": 1
    },
    {
        "id": 83,
        "question": "من هو العالم الإسلامي المعروف بعمله على الأسطرلاب والجداول الفلكية؟",
        "answers": [
            "الخوارزمي",
            "البَطّاني",
            "البيروني",
            "ابن الهيثم"
        ],
        "correctAnswer": 1
    },
    {
        "id": 84,
        "question": "أي خليفة معروف بجمع القرآن في كتاب واحد؟",
        "answers": [
            "أبو بكر الصديق",
            "عمر بن الخطاب",
            "عثمان بن عفان",
            "علي بن أبي طالب"
        ],
        "correctAnswer": 2
    },
    {
        "id": 85,
        "question": "أي إمبراطورية معروفة بالتحفة المعمارية، الحمراء؟",
        "answers": [
            "الخلافة الأموية",
            "الخلافة العباسية",
            "الخلافة الفاطمية",
            "مملكة بني نصر"
        ],
        "correctAnswer": 3
    },
    {
        "id": 86,
        "question": "أي خلافة معروفة بعاصمتها، دمشق؟",
        "answers": [
            "الخلافة الأموية",
            "الخلافة العباسية",
            "الخلافة الفاطمية",
            "الإمبراطورية العثمانية"
        ],
        "correctAnswer": 0
    },
    {
        "id": 87,
        "question": "من هو الجغرافي ورسام الخرائط المسلم الشهير بخريطته العالمية؟",
        "answers": [
            "المسعودي",
            "ابن بطوطة",
            "الإدريسي",
            "ابن جبير"
        ],
        "correctAnswer": 2
    },
    {
        "id": 88,
        "question": "أي معركة تعرف أيضًا باسم 'معركة الجمل'؟",
        "answers": [
            "معركة بدر",
            "معركة أحد",
            "معركة الجمل",
            "معركة صفين"
        ],
        "correctAnswer": 2
    },
    {
        "id": 89,
        "question": "من هو أول خليفة في الخلافة العباسية؟",
        "answers": [
            "أبو العباس السفاح",
            "المنصور",
            "هارون الرشيد",
            "المأمون"
        ],
        "correctAnswer": 0
    },
    {
        "id": 90,
        "question": "أي إمبراطورية إسلامية أسسها عثمان الأول؟",
        "answers": [
            "الخلافة الأموية",
            "الخلافة العباسية",
            "الإمبراطورية السلجوقية",
            "الإمبراطورية العثمانية"
        ],
        "correctAnswer": 3
    },
    {
        "id": 91,
        "question": "من هو الفيلسوف الإسلامي المعروف بعمله 'تهافت الفلاسفة'؟",
        "answers": [
            "ابن سينا",
            "الغزالي",
            "ابن رشد",
            "الفارابي"
        ],
        "correctAnswer": 1
    },
    {
        "id": 92,
        "question": "أي حاكم إسلامي أمر ببناء المسجد الكبير في سامراء؟",
        "answers": [
            "المنصور",
            "المأمون",
            "المتوكل",
            "هارون الرشيد"
        ],
        "correctAnswer": 2
    },
    {
        "id": 93,
        "question": "من هو عالم الرياضيات المسلم المعروف باختراع الجبر؟",
        "answers": [
            "ابن سينا",
            "الخوارزمي",
            "الرازي",
            "البيروني"
        ],
        "correctAnswer": 1
    },
    {
        "id": 94,
        "question": "أي معركة تعرف أيضًا باسم 'معركة الخندق'؟",
        "answers": [
            "معركة بدر",
            "معركة أحد",
            "معركة الخندق",
            "معركة تبوك"
        ],
        "correctAnswer": 2
    },
    {
        "id": 95,
        "question": "من هو المستكشف المسلم الذي سافر بشكل واسع في أفريقيا وآسيا ووثق رحلاته؟",
        "answers": [
            "ابن بطوطة",
            "المسعودي",
            "الإدريسي",
            "ابن جبير"
        ],
        "correctAnswer": 0
    },
    {
        "id": 96,
        "question": "أي خليفة معروف بتوسيع الإمبراطورية الإسلامية لتشمل مصر وفارس وأجزاء من الإمبراطورية البيزنطية؟",
        "answers": [
            "أبو بكر الصديق",
            "عمر بن الخطاب",
            "عثمان بن عفان",
            "علي بن أبي طالب"
        ],
        "correctAnswer": 1
    },
    {
        "id": 97,
        "question": "أي خليفة إسلامي معروف بتوحيد القرآن؟",
        "answers": [
            "أبو بكر الصديق",
            "عمر بن الخطاب",
            "عثمان بن عفان",
            "علي بن أبي طالب"
        ],
        "correctAnswer": 2
    },
    {
        "id": 98,
        "question": "أي عالم إسلامي معروف بموسوعته الطبية الشاملة 'القانون في الطب'؟",
        "answers": [
            "الكندي",
            "ابن سينا",
            "الرازي",
            "الزهراوي"
        ],
        "correctAnswer": 1
    },
    {
        "id": 99,
        "question": "أي إمبراطورية إسلامية معروفة ببناء قصر الحمراء في غرناطة؟",
        "answers": [
            "الخلافة الأموية",
            "الخلافة العباسية",
            "الخلافة الفاطمية",
            "مملكة بني نصر"
        ],
        "correctAnswer": 3
    },
    {
        "id": 100,
        "question": "من هو أول خليفة استخدم لقب 'أمير المؤمنين'؟",
        "answers": [
            "أبو بكر الصديق",
            "عمر بن الخطاب",
            "عثمان بن عفان",
            "علي بن أبي طالب"
        ],
        "correctAnswer": 1
    }
]